{
  "UserAgent": "MobileHub/1.0",
  "Version": "1.0",
  "CredentialsProvider": {
    "CognitoIdentity": {
      "Default": {
        "PoolId": "us-east-1:043e8dba-50d8-45dc-a776-518b0a9c4fc8",
        "Region": "us-east-1"
      }
    }
  },
  "IdentityManager": {
    "Default": {}
  },
  "PinpointAnalytics": {
    "Default": {
      "AppId": "50cbc9aac9054ad492117d480156b9d3",
      "Region": "us-east-1"
    }
  },
  "PinpointTargeting": {
    "Default": {
      "Region": "us-east-1"
    }
  }
}